setup.cfg
setup.py
interpreter/__init__.py
interpreter/element.py
interpreter/expression.py
interpreter/lambda_element.py
interpreter/operator.py
interpreter/variable.py
lambda_interpreter.egg-info/PKG-INFO
lambda_interpreter.egg-info/SOURCES.txt
lambda_interpreter.egg-info/dependency_links.txt
lambda_interpreter.egg-info/top_level.txt