Metadata-Version: 1.0
Name: lambda-interpreter
Version: 1.1
Summary: This projects aim is to evaluate lambda calculus expressions.
Home-page: https://bitbucket.org/simonasya/lambda-interpreter
Author: Simona Kurnavova
Author-email: simasya.k@gmail.com
License: GNU General Public License v3.0
Platform: UNKNOWN
